fmsc/__init__.py
fmsc/__main__.py
fmsc/aioupgrade.py
fmsc/aupfile.py
fmsc/aupparser.py
fmsc/cgminerapi.py
fmsc/cliprogressbar.py
fmsc/upgrade.py
fmsc/utils.py
fms_core-0.0.3.dist-info/LICENSE
fms_core-0.0.3.dist-info/METADATA
fms_core-0.0.3.dist-info/WHEEL
fms_core-0.0.3.dist-info/entry_points.txt
fms_core-0.0.3.dist-info/top_level.txt
fms_core-0.0.3.dist-info/RECORD
