Metadata-Version: 2.1
Name: fms-core
Version: 0.0.3
Summary: The core functions that Canaan FMS and other miner management systems needed to communicate with and control Avalon miners.
Home-page: https://github.com/Canaan-Creative/fms-core
Author: Canaan
Author-email: 
License: Apache-2.0
Platform: UNKNOWN
Classifier: License :: OSI Approved :: Apache Software License
Classifier: Programming Language :: Python :: 3 :: Only
Requires-Dist: kaitaistruct
